{
  "title": "Linux networking practice",
  "description": "This is the description of LNP",
  "details": {
    "intro": {
      "text": "service/intro.md",
      "foreground": "scripts/foreground.sh"
    },
    "steps": [
      {
        "title": "'ip' and 'ethtool' utilities",
        "text": "ip_ethtool.md"
      },{
        "title": "systemd-networkd — Network manager",
        "text": "networkd.md"
      },{
        "title": "Configuring network with NetPlan",
        "text": "netplan.md"
      },{
        "title": "Packet management with iptables",
        "text": "netfilter.md"
      },{
        "title": "Monitoring network activity",
        "text": "activity.md"
      },{
        "title": "Analyze network traffic",
        "text": "traffic.md"
      }
    ],
    "finish": {
      "text": "service/finish.md"
    }
  },
  "backend": {
    "imageid": "ubuntu"
  }
}
